openzgy/__init__.py
openzgy/api.py
openzgy/exception.py
openzgy/iterator.py
openzgy/zgypublic.py
openzgy/impl/__init__.py
openzgy/impl/bulk.py
openzgy/impl/compress.py
openzgy/impl/enum.py
openzgy/impl/file.py
openzgy/impl/genlod.py
openzgy/impl/histogram.py
openzgy/impl/lodalgo.py
openzgy/impl/meta.py
openzgy/impl/stats.py
openzgy/impl/transform.py
openzgy/impl/zfp_compress.py
openzgy/test/__init__.py
openzgy/test/black.py
openzgy/test/file.py
openzgy/test/iterator.py
openzgy/test/lodalgo.py
openzgy/test/utils.py
openzgy/test/white.py
openzgy/tools/__init__.py
openzgy/tools/badtrace.py
openzgy/tools/compare.py
openzgy/tools/compresstest.py
openzgy/tools/copy.py
openzgy/tools/cppmeta.py
openzgy/tools/dumphist.py
openzgy/tools/evalnoise.py
openzgy/tools/gui_copy.py
openzgy/tools/histcheck.py
openzgy/tools/isoptimal.py
openzgy/tools/show.py
openzgy/tools/simplecopy.py
openzgy/tools/speedtest.py
openzgy/tools/viewzgy.py
openzgy/tools/zgydump.py
pyzgy/__init__.py
pyzgy/accessors.py
pyzgy/loader.py
pyzgy/open.py
pyzgy/read.py
pyzgy/tools.py
pyzgy/write.py
pyzgy/xarray.py
pyzgy-0.1.1.dist-info/LICENSE.txt
pyzgy-0.1.1.dist-info/METADATA
pyzgy-0.1.1.dist-info/WHEEL
pyzgy-0.1.1.dist-info/entry_points.txt
pyzgy-0.1.1.dist-info/top_level.txt
pyzgy-0.1.1.dist-info/RECORD
