Metadata-Version: 2.2
Name: pyzgy
Version: 0.1.1
Summary: Convenience wrapper around OpenZGY Python implementation
Author: equinor
License:                                  Apache License
Project-URL: Repository, https://github.com/equinor/pyzgy
Classifier: License :: OSI Approved :: Apache Software License
Requires-Python: >=3.9
License-File: LICENSE.txt
Requires-Dist: numpy>=1.20
Requires-Dist: segyio
Requires-Dist: xarray
Requires-Dist: dask
